{
  "tabPane": [
    {
      "title": "Driver View",
      "autoPopulate": false,
      "autoPopulatePrefix": "SmartDashboard/",
      "widgetPane": {
        "gridSize": 100.0,
        "showGrid": true,
        "hgap": 16.0,
        "vgap": 16.0,
        "titleType": 0,
        "tiles": {
          "0,7": {
            "size": [
              3,
              1
            ],
            "content": {
              "_type": "ComboBox Chooser",
              "_source0": "network_table:///SmartDashboard/Starting Position?",
              "_title": "Starting Position?",
              "_glyph": 148,
              "_showGlyph": false
            }
          },
          "4,7": {
            "size": [
              3,
              1
            ],
            "content": {
              "_type": "ComboBox Chooser",
              "_source0": "network_table:///SmartDashboard/Grabbing First Piece?",
              "_title": "SmartDashboard/Grabbing First Piece?",
              "_glyph": 148,
              "_showGlyph": false
            }
          },
          "8,7": {
            "size": [
              3,
              1
            ],
            "content": {
              "_type": "ComboBox Chooser",
              "_source0": "network_table:///SmartDashboard/Grabbing Second Piece?",
              "_title": "SmartDashboard/Grabbing Second Piece?",
              "_glyph": 148,
              "_showGlyph": false
            }
          },
          "12,7": {
            "size": [
              3,
              1
            ],
            "content": {
              "_type": "ComboBox Chooser",
              "_source0": "network_table:///SmartDashboard/Balancing on Charge Station?",
              "_title": "SmartDashboard/Balancing on Charge Station?",
              "_glyph": 148,
              "_showGlyph": false
            }
          },
          "4,4": {
            "size": [
              1,
              1
            ],
            "content": {
              "_type": "Boolean Box",
              "_title": "Intake On?",
              "_glyph": 148,
              "_showGlyph": false,
              "Colors/Color when true": "#7CFC00FF",
              "Colors/Color when false": "#8B0000FF"
            }
          },
          "5,4": {
            "size": [
              1,
              1
            ],
            "content": {
              "_type": "Boolean Box",
              "_title": "Turntable On?",
              "_glyph": 148,
              "_showGlyph": false,
              "Colors/Color when true": "#7CFC00FF",
              "Colors/Color when false": "#8B0000FF"
            }
          },
          "1,3": {
            "size": [
              1,
              1
            ],
            "content": {
              "_type": "Boolean Box",
              "_title": "Have Piece?",
              "_glyph": 148,
              "_showGlyph": false,
              "Colors/Color when true": "#7CFC00FF",
              "Colors/Color when false": "#8B0000FF"
            }
          },
          "0,3": {
            "size": [
              1,
              1
            ],
            "content": {
              "_type": "Boolean Box",
              "_title": "Grab Ready?",
              "_glyph": 148,
              "_showGlyph": false,
              "Colors/Color when true": "#7CFC00FF",
              "Colors/Color when false": "#8B0000FF"
            }
          },
          "3,4": {
            "size": [
              1,
              1
            ],
            "content": {
              "_type": "Boolean Box",
              "_title": "Place Ready?",
              "_glyph": 148,
              "_showGlyph": false,
              "Colors/Color when true": "#7CFC00FF",
              "Colors/Color when false": "#8B0000FF"
            }
          },
          "3,5": {
            "size": [
              4,
              1
            ],
            "content": {
              "_type": "ComboBox Chooser",
              "_source0": "network_table:///SmartDashboard/Auto Chooser",
              "_title": "SmartDashboard/Auto Chooser",
              "_glyph": 148,
              "_showGlyph": false
            }
          },
          "7,3": {
            "size": [
              5,
              3
            ],
            "content": {
              "_type": "Field",
              "_source0": "network_table:///SmartDashboard/Field",
              "_title": "SmartDashboard/Field",
              "_glyph": 148,
              "_showGlyph": false,
              "Game/Game": "k2024Crescendo",
              "Visuals/Robot Icon Size": 50.0,
              "Visuals/Show Outside Circles": false,
              "Colors/Auto Path": "#FFFFFFFF"
            }
          },
          "1,0": {
            "size": [
              4,
              3
            ],
            "content": {
              "_type": "Camera Stream",
              "_source0": "camera_server://limelight-fight",
              "_title": "limelight-fight",
              "_glyph": 148,
              "_showGlyph": false,
              "Crosshair/Show crosshair": true,
              "Crosshair/Crosshair color": "#FFFFFFFF",
              "Controls/Show controls": true,
              "Controls/Rotation": "NONE",
              "compression": -1.0,
              "fps": -1,
              "imageWidth": 0,
              "imageHeight": 0
            }
          },
          "6,0": {
            "size": [
              4,
              3
            ],
            "content": {
              "_type": "Camera Stream",
              "_source0": "camera_server://limelight-bite",
              "_title": "limelight-bite",
              "_glyph": 148,
              "_showGlyph": false,
              "Crosshair/Show crosshair": true,
              "Crosshair/Crosshair color": "#FFFFFFFF",
              "Controls/Show controls": true,
              "Controls/Rotation": "NONE",
              "compression": -1.0,
              "fps": -1,
              "imageWidth": -1,
              "imageHeight": -1
            }
          }
        }
      }
    },
    {
      "title": "Debug",
      "autoPopulate": true,
      "autoPopulatePrefix": "LiveWindow/",
      "widgetPane": {
        "gridSize": 100.0,
        "showGrid": true,
        "hgap": 16.0,
        "vgap": 16.0,
        "titleType": 0,
        "tiles": {
          "6,1": {
            "size": [
              4,
              4
            ],
            "content": {
              "_type": "PDP",
              "_source0": "network_table:///SmartDashboard/PDP",
              "_title": "SmartDashboard/PDP",
              "_glyph": 148,
              "_showGlyph": false,
              "Visuals/Show voltage and current values": true
            }
          }
        }
      }
    },
    {
      "title": "Limelight",
      "autoPopulate": true,
      "autoPopulatePrefix": "limelight-subsystem",
      "widgetPane": {
        "gridSize": 128.0,
        "showGrid": true,
        "hgap": 16.0,
        "vgap": 16.0,
        "titleType": 0,
        "tiles": {
          "0,0": {
            "size": [
              1,
              1
            ],
            "content": {
              "_type": "Text View",
              "_source0": "network_table:///limelight-subsystem/distanceToSpeaker",
              "_title": "/distanceToSpeaker",
              "_glyph": 148,
              "_showGlyph": false
            }
          },
          "1,0": {
            "size": [
              1,
              1
            ],
            "content": {
              "_type": "Text View",
              "_source0": "network_table:///limelight-subsystem/angleToSpeaker",
              "_title": "/angleToSpeaker",
              "_glyph": 148,
              "_showGlyph": false
            }
          },
          "2,0": {
            "size": [
              1,
              1
            ],
            "content": {
              "_type": "Boolean Box",
              "_source0": "network_table:///limelight-subsystem/Saw April Tag",
              "_title": "/Saw April Tag",
              "_glyph": 148,
              "_showGlyph": false,
              "Colors/Color when true": "#7CFC00FF",
              "Colors/Color when false": "#8B0000FF"
            }
          },
          "3,0": {
            "size": [
              1,
              1
            ],
            "content": {
              "_type": "Text View",
              "_source0": "network_table:///limelight-subsystem/poseEstimator Timestamp",
              "_title": "/poseEstimator Timestamp",
              "_glyph": 148,
              "_showGlyph": false
            }
          },
          "4,0": {
            "size": [
              1,
              1
            ],
            "content": {
              "_type": "Text View",
              "_source0": "network_table:///limelight-subsystem/current Timestamp",
              "_title": "/current Timestamp",
              "_glyph": 148,
              "_showGlyph": false
            }
          },
          "5,0": {
            "size": [
              1,
              1
            ],
            "content": {
              "_type": "Text View",
              "_source0": "network_table:///limelight-subsystem/noteTX",
              "_title": "/noteTX",
              "_glyph": 148,
              "_showGlyph": false
            }
          }
        }
      }
    },
    {
      "title": "Intake",
      "autoPopulate": true,
      "autoPopulatePrefix": "intake-table",
      "widgetPane": {
        "gridSize": 128.0,
        "showGrid": true,
        "hgap": 16.0,
        "vgap": 16.0,
        "titleType": 0,
        "tiles": {
          "5,2": {
            "size": [
              2,
              2
            ],
            "content": {
              "_type": "Boolean Box",
              "_source0": "network_table:///intake-table/Beam Broken",
              "_title": "/intake-table/Beam Broken",
              "_glyph": 148,
              "_showGlyph": false,
              "Colors/Color when true": "#7CFC00FF",
              "Colors/Color when false": "#8B0000FF"
            }
          },
          "0,0": {
            "size": [
              1,
              1
            ],
            "content": {
              "_type": "Boolean Box",
              "_source0": "network_table:///intake-table/Intake On",
              "_title": "/Intake On",
              "_glyph": 148,
              "_showGlyph": false,
              "Colors/Color when true": "#7CFC00FF",
              "Colors/Color when false": "#8B0000FF"
            }
          },
          "1,0": {
            "size": [
              1,
              1
            ],
            "content": {
              "_type": "Boolean Box",
              "_source0": "network_table:///intake-table/Intake Fire",
              "_title": "/Intake Fire",
              "_glyph": 148,
              "_showGlyph": false,
              "Colors/Color when true": "#7CFC00FF",
              "Colors/Color when false": "#8B0000FF"
            }
          },
          "2,0": {
            "size": [
              1,
              1
            ],
            "content": {
              "_type": "Boolean Box",
              "_source0": "network_table:///intake-table/Intake Yuck",
              "_title": "/Intake Yuck",
              "_glyph": 148,
              "_showGlyph": false,
              "Colors/Color when true": "#7CFC00FF",
              "Colors/Color when false": "#8B0000FF"
            }
          },
          "3,0": {
            "size": [
              1,
              1
            ],
            "content": {
              "_type": "Boolean Box",
              "_source0": "network_table:///intake-table/Intake BeamBreak",
              "_title": "/Intake BeamBreak",
              "_glyph": 148,
              "_showGlyph": false,
              "Colors/Color when true": "#7CFC00FF",
              "Colors/Color when false": "#8B0000FF"
            }
          }
        }
      }
    },
    {
      "title": "Shooter",
      "autoPopulate": true,
      "autoPopulatePrefix": "shooter-subsystem",
      "widgetPane": {
        "gridSize": 128.0,
        "showGrid": true,
        "hgap": 16.0,
        "vgap": 16.0,
        "titleType": 0,
        "tiles": {
          "11,0": {
            "size": [
              1,
              1
            ],
            "content": {
              "_type": "Text View",
              "_source0": "network_table:///shooter-subsystem/backMotor Setpoint",
              "_title": "/backMotor Setpoint",
              "_glyph": 148,
              "_showGlyph": false
            }
          },
          "12,0": {
            "size": [
              1,
              1
            ],
            "content": {
              "_type": "Text View",
              "_source0": "network_table:///shooter-subsystem/Shooter kV",
              "_title": "/Shooter kV",
              "_glyph": 148,
              "_showGlyph": false
            }
          },
          "2,1": {
            "size": [
              1,
              1
            ],
            "content": {
              "_type": "Text View",
              "_source0": "network_table:///shooter-subsystem/Shooter kP",
              "_title": "/Shooter kP",
              "_glyph": 148,
              "_showGlyph": false
            }
          },
          "3,1": {
            "size": [
              1,
              1
            ],
            "content": {
              "_type": "Text View",
              "_source0": "network_table:///shooter-subsystem/Shooter kI",
              "_title": "/Shooter kI",
              "_glyph": 148,
              "_showGlyph": false
            }
          },
          "4,1": {
            "size": [
              1,
              1
            ],
            "content": {
              "_type": "Text View",
              "_source0": "network_table:///shooter-subsystem/Shooter kD",
              "_title": "/Shooter kD",
              "_glyph": 148,
              "_showGlyph": false
            }
          },
          "2,2": {
            "size": [
              2,
              1
            ],
            "content": {
              "_type": "Boolean Box",
              "_source0": "network_table:///shooter-subsystem/Shooter At Speed",
              "_title": "/Shooter At Speed",
              "_glyph": 148,
              "_showGlyph": false,
              "Colors/Color when true": "#7CFC00FF",
              "Colors/Color when false": "#8B0000FF"
            }
          },
          "7,1": {
            "size": [
              2,
              1
            ],
            "content": {
              "_type": "Text View",
              "_source0": "network_table:///shooter-subsystem/leftMotor Velocity",
              "_title": "/leftMotor Velocity",
              "_glyph": 148,
              "_showGlyph": false
            }
          },
          "11,1": {
            "size": [
              1,
              1
            ],
            "content": {
              "_type": "Text View",
              "_source0": "network_table:///shooter-subsystem/rightMotor Velocity",
              "_title": "/rightMotor Velocity",
              "_glyph": 148,
              "_showGlyph": false
            }
          },
          "5,1": {
            "size": [
              2,
              1
            ],
            "content": {
              "_type": "Text View",
              "_source0": "network_table:///shooter-subsystem/leftMotor Setpoint",
              "_title": "shooter-subsystem/leftMotor Setpoint",
              "_glyph": 148,
              "_showGlyph": false
            }
          },
          "5,2": {
            "size": [
              2,
              1
            ],
            "content": {
              "_type": "Text View",
              "_source0": "network_table:///shooter-subsystem/rightMotor Setpoint",
              "_title": "shooter-subsystem/rightMotor Setpoint",
              "_glyph": 148,
              "_showGlyph": false
            }
          },
          "0,0": {
            "size": [
              1,
              1
            ],
            "content": {
              "_type": "Text View",
              "_source0": "network_table:///shooter-subsystem/rightOutput",
              "_title": "/rightOutput",
              "_glyph": 148,
              "_showGlyph": false
            }
          }
        }
      }
    },
    {
      "title": "Trigger",
      "autoPopulate": true,
      "autoPopulatePrefix": "trigger-subsystem",
      "widgetPane": {
        "gridSize": 128.0,
        "showGrid": true,
        "hgap": 16.0,
        "vgap": 16.0,
        "titleType": 0,
        "tiles": {
          "0,0": {
            "size": [
              1,
              1
            ],
            "content": {
              "_type": "Text View",
              "_source0": "network_table:///trigger-velocity-PID/Trigger Speed",
              "_title": "igger-velocity-PID/Trigger Speed",
              "_glyph": 148,
              "_showGlyph": false
            }
          },
          "1,0": {
            "size": [
              1,
              1
            ],
            "content": {
              "_type": "Text View",
              "_source0": "network_table:///trigger-velocity-PID/Trigger kV",
              "_title": "igger-velocity-PID/Trigger kV",
              "_glyph": 148,
              "_showGlyph": false
            }
          },
          "2,0": {
            "size": [
              1,
              1
            ],
            "content": {
              "_type": "Text View",
              "_source0": "network_table:///trigger-velocity-PID/Trigger kP",
              "_title": "igger-velocity-PID/Trigger kP",
              "_glyph": 148,
              "_showGlyph": false
            }
          },
          "3,0": {
            "size": [
              1,
              1
            ],
            "content": {
              "_type": "Text View",
              "_source0": "network_table:///trigger-velocity-PID/Trigger kI",
              "_title": "igger-velocity-PID/Trigger kI",
              "_glyph": 148,
              "_showGlyph": false
            }
          },
          "4,0": {
            "size": [
              1,
              1
            ],
            "content": {
              "_type": "Text View",
              "_source0": "network_table:///trigger-velocity-PID/Trigger kD",
              "_title": "igger-velocity-PID/Trigger kD",
              "_glyph": 148,
              "_showGlyph": false
            }
          },
          "5,0": {
            "size": [
              1,
              1
            ],
            "content": {
              "_type": "Text View",
              "_source0": "network_table:///trigger-velocity-PID/triggerMotor Velocity",
              "_title": "igger-velocity-PID/triggerMotor Velocity",
              "_glyph": 148,
              "_showGlyph": false
            }
          },
          "6,0": {
            "size": [
              1,
              1
            ],
            "content": {
              "_type": "Text View",
              "_source0": "network_table:///trigger-subsystem/Trigger Setpoint",
              "_title": "/Trigger Setpoint",
              "_glyph": 148,
              "_showGlyph": false
            }
          },
          "7,0": {
            "size": [
              1,
              1
            ],
            "content": {
              "_type": "Text View",
              "_source0": "network_table:///trigger-subsystem/Trigger kV",
              "_title": "/Trigger kV",
              "_glyph": 148,
              "_showGlyph": false
            }
          },
          "8,0": {
            "size": [
              1,
              1
            ],
            "content": {
              "_type": "Text View",
              "_source0": "network_table:///trigger-subsystem/Trigger kP",
              "_title": "/Trigger kP",
              "_glyph": 148,
              "_showGlyph": false
            }
          },
          "9,0": {
            "size": [
              1,
              1
            ],
            "content": {
              "_type": "Text View",
              "_source0": "network_table:///trigger-subsystem/Trigger kI",
              "_title": "/Trigger kI",
              "_glyph": 148,
              "_showGlyph": false
            }
          },
          "10,0": {
            "size": [
              1,
              1
            ],
            "content": {
              "_type": "Text View",
              "_source0": "network_table:///trigger-subsystem/Trigger kD",
              "_title": "/Trigger kD",
              "_glyph": 148,
              "_showGlyph": false
            }
          },
          "11,0": {
            "size": [
              1,
              1
            ],
            "content": {
              "_type": "Text View",
              "_source0": "network_table:///trigger-subsystem/triggerMotor Velocity",
              "_title": "/triggerMotor Velocity",
              "_glyph": 148,
              "_showGlyph": false
            }
          },
          "12,0": {
            "size": [
              1,
              1
            ],
            "content": {
              "_type": "Boolean Box",
              "_source0": "network_table:///trigger-subsystem/Beam Broken",
              "_title": "/Beam Broken",
              "_glyph": 148,
              "_showGlyph": false,
              "Colors/Color when true": "#7CFC00FF",
              "Colors/Color when false": "#8B0000FF"
            }
          },
          "0,1": {
            "size": [
              1,
              1
            ],
            "content": {
              "_type": "Boolean Box",
              "_source0": "network_table:///trigger-subsystem/Trigger On",
              "_title": "/Trigger On",
              "_glyph": 148,
              "_showGlyph": false,
              "Colors/Color when true": "#7CFC00FF",
              "Colors/Color when false": "#8B0000FF"
            }
          },
          "1,1": {
            "size": [
              1,
              1
            ],
            "content": {
              "_type": "Boolean Box",
              "_source0": "network_table:///trigger-subsystem/Trigger Fire",
              "_title": "/Trigger Fire",
              "_glyph": 148,
              "_showGlyph": false,
              "Colors/Color when true": "#7CFC00FF",
              "Colors/Color when false": "#8B0000FF"
            }
          },
          "2,1": {
            "size": [
              1,
              1
            ],
            "content": {
              "_type": "Boolean Box",
              "_source0": "network_table:///trigger-subsystem/Trigger Yuck",
              "_title": "/Trigger Yuck",
              "_glyph": 148,
              "_showGlyph": false,
              "Colors/Color when true": "#7CFC00FF",
              "Colors/Color when false": "#8B0000FF"
            }
          },
          "3,1": {
            "size": [
              1,
              1
            ],
            "content": {
              "_type": "Boolean Box",
              "_source0": "network_table:///trigger-subsystem/Trigger BeamBreak",
              "_title": "/Trigger BeamBreak",
              "_glyph": 148,
              "_showGlyph": false,
              "Colors/Color when true": "#7CFC00FF",
              "Colors/Color when false": "#8B0000FF"
            }
          }
        }
      }
    },
    {
      "title": "Pivot",
      "autoPopulate": true,
      "autoPopulatePrefix": "pivot-table",
      "widgetPane": {
        "gridSize": 128.0,
        "showGrid": true,
        "hgap": 16.0,
        "vgap": 16.0,
        "titleType": 0,
        "tiles": {
          "1,1": {
            "size": [
              2,
              1
            ],
            "content": {
              "_type": "Text View",
              "_source0": "network_table:///pivot-table/Absolute Encoder Position",
              "_title": "t-table/Absolute Encoder Position",
              "_glyph": 148,
              "_showGlyph": false
            }
          },
          "4,2": {
            "size": [
              1,
              1
            ],
            "content": {
              "_type": "Text View",
              "_source0": "network_table:///pivot-table/Pivot Power",
              "_title": "t-table/Pivot Power",
              "_glyph": 148,
              "_showGlyph": false
            }
          },
          "4,0": {
            "size": [
              3,
              1
            ],
            "content": {
              "_type": "Text View",
              "_source0": "network_table:///pivot-table/Pivot Position",
              "_title": "t-table/Pivot Position",
              "_glyph": 148,
              "_showGlyph": false
            }
          },
          "0,0": {
            "size": [
              1,
              1
            ],
            "content": {
              "_type": "Text View",
              "_source0": "network_table:///pivot-table/kP",
              "_title": "/kP",
              "_glyph": 148,
              "_showGlyph": false
            }
          },
          "2,0": {
            "size": [
              1,
              1
            ],
            "content": {
              "_type": "Text View",
              "_source0": "network_table:///pivot-table/kI",
              "_title": "/kI",
              "_glyph": 148,
              "_showGlyph": false
            }
          },
          "3,0": {
            "size": [
              1,
              1
            ],
            "content": {
              "_type": "Text View",
              "_source0": "network_table:///pivot-table/kD",
              "_title": "/kD",
              "_glyph": 148,
              "_showGlyph": false
            }
          },
          "7,1": {
            "size": [
              1,
              1
            ],
            "content": {
              "_type": "Text View",
              "_source0": "network_table:///pivot-table/P Proportion",
              "_title": "/P Proportion",
              "_glyph": 148,
              "_showGlyph": false
            }
          },
          "8,1": {
            "size": [
              1,
              1
            ],
            "content": {
              "_type": "Text View",
              "_source0": "network_table:///pivot-table/D Proportion",
              "_title": "/D Proportion",
              "_glyph": 148,
              "_showGlyph": false
            }
          },
          "1,2": {
            "size": [
              3,
              1
            ],
            "content": {
              "_type": "Text View",
              "_source0": "network_table:///pivot-table/Grav Propotion",
              "_title": "/Grav Propotion",
              "_glyph": 148,
              "_showGlyph": false
            }
          },
          "1,0": {
            "size": [
              1,
              1
            ],
            "content": {
              "_type": "Text View",
              "_source0": "network_table:///pivot-table/Pivot Setpoint",
              "_title": "/Pivot Setpoint",
              "_glyph": 148,
              "_showGlyph": false
            }
          },
          "7,0": {
            "size": [
              1,
              1
            ],
            "content": {
              "_type": "Text View",
              "_source0": "network_table:///pivot-table/Pivot Error",
              "_title": "/Pivot Error",
              "_glyph": 148,
              "_showGlyph": false
            }
          },
          "8,0": {
            "size": [
              1,
              1
            ],
            "content": {
              "_type": "Text View",
              "_source0": "network_table:///pivot-table/Pivot Angle",
              "_title": "/Pivot Angle",
              "_glyph": 148,
              "_showGlyph": false
            }
          },
          "3,1": {
            "size": [
              1,
              1
            ],
            "content": {
              "_type": "Text View",
              "_source0": "network_table:///pivot-table/kG",
              "_title": "/kG",
              "_glyph": 148,
              "_showGlyph": false
            }
          },
          "9,0": {
            "size": [
              1,
              1
            ],
            "content": {
              "_type": "Text View",
              "_source0": "network_table:///pivot-table/Commanded Output",
              "_title": "/Commanded Output",
              "_glyph": 148,
              "_showGlyph": false
            }
          },
          "0,1": {
            "size": [
              1,
              1
            ],
            "content": {
              "_type": "Text View",
              "_source0": "network_table:///pivot-table/Filtered Input",
              "_title": "/Filtered Input",
              "_glyph": 148,
              "_showGlyph": false
            }
          },
          "4,1": {
            "size": [
              1,
              1
            ],
            "content": {
              "_type": "Text View",
              "_source0": "network_table:///pivot-table/magicEncoderValue",
              "_title": "/magicEncoderValue",
              "_glyph": 148,
              "_showGlyph": false
            }
          },
          "9,1": {
            "size": [
              1,
              1
            ],
            "content": {
              "_type": "Text View",
              "_source0": "network_table:///pivot-table/Pivot Right Current",
              "_title": "/Pivot Right Current",
              "_glyph": 148,
              "_showGlyph": false
            }
          },
          "5,1": {
            "size": [
              2,
              1
            ],
            "content": {
              "_type": "Text View",
              "_source0": "network_table:///pivot-table/Pivot Test Set Point",
              "_title": "pivot-table/Pivot Test Set Point",
              "_glyph": 148,
              "_showGlyph": false
            }
          },
          "0,2": {
            "size": [
              1,
              1
            ],
            "content": {
              "_type": "Boolean Box",
              "_source0": "network_table:///pivot-table/is Pivot abs Working",
              "_title": "/is Pivot abs Working",
              "_glyph": 148,
              "_showGlyph": false,
              "Colors/Color when true": "#7CFC00FF",
              "Colors/Color when false": "#8B0000FF"
            }
          }
        }
      }
    },
    {
      "title": "Climber",
      "autoPopulate": true,
      "autoPopulatePrefix": "climber-table",
      "widgetPane": {
        "gridSize": 128.0,
        "showGrid": true,
        "hgap": 16.0,
        "vgap": 16.0,
        "titleType": 0,
        "tiles": {
          "0,0": {
            "size": [
              1,
              1
            ],
            "content": {
              "_type": "Text View",
              "_source0": "network_table:///climber-table/Climber kP",
              "_title": "/Climber kP",
              "_glyph": 148,
              "_showGlyph": false
            }
          },
          "1,0": {
            "size": [
              1,
              1
            ],
            "content": {
              "_type": "Text View",
              "_source0": "network_table:///climber-table/Climber kI",
              "_title": "/Climber kI",
              "_glyph": 148,
              "_showGlyph": false
            }
          },
          "2,0": {
            "size": [
              1,
              1
            ],
            "content": {
              "_type": "Text View",
              "_source0": "network_table:///climber-table/Climber kD",
              "_title": "/Climber kD",
              "_glyph": 148,
              "_showGlyph": false
            }
          },
          "3,0": {
            "size": [
              1,
              1
            ],
            "content": {
              "_type": "Text View",
              "_source0": "network_table:///climber-table/Climber kIz",
              "_title": "/Climber kIz",
              "_glyph": 148,
              "_showGlyph": false
            }
          },
          "4,0": {
            "size": [
              1,
              1
            ],
            "content": {
              "_type": "Text View",
              "_source0": "network_table:///climber-table/Climber kFF",
              "_title": "/Climber kFF",
              "_glyph": 148,
              "_showGlyph": false
            }
          },
          "5,0": {
            "size": [
              1,
              1
            ],
            "content": {
              "_type": "Text View",
              "_source0": "network_table:///climber-table/Climber Left Motor Encoder",
              "_title": "/Climber Left Motor Encoder",
              "_glyph": 148,
              "_showGlyph": false
            }
          },
          "6,0": {
            "size": [
              1,
              1
            ],
            "content": {
              "_type": "Text View",
              "_source0": "network_table:///climber-table/Climber Right Motor Encoder",
              "_title": "/Climber Right Motor Encoder",
              "_glyph": 148,
              "_showGlyph": false
            }
          },
          "4,1": {
            "size": [
              2,
              1
            ],
            "content": {
              "_type": "Text View",
              "_source0": "network_table:///climber-table/Climber Left Motor Encoder",
              "_title": "climber-table/Climber Left Motor Encoder",
              "_glyph": 148,
              "_showGlyph": false
            }
          },
          "4,2": {
            "size": [
              2,
              1
            ],
            "content": {
              "_type": "Text View",
              "_source0": "network_table:///climber-table/Climber Right Motor Encoder",
              "_title": "climber-table/Climber Right Motor Encoder",
              "_glyph": 148,
              "_showGlyph": false
            }
          },
          "7,0": {
            "size": [
              1,
              1
            ],
            "content": {
              "_type": "Text View",
              "_source0": "network_table:///climber-table/Climber Left Motor Raw Encoder",
              "_title": "/Climber Left Motor Raw Encoder",
              "_glyph": 148,
              "_showGlyph": false
            }
          },
          "8,0": {
            "size": [
              1,
              1
            ],
            "content": {
              "_type": "Text View",
              "_source0": "network_table:///climber-table/Climber Right Motor Raw Encoder",
              "_title": "/Climber Right Motor Raw Encoder",
              "_glyph": 148,
              "_showGlyph": false
            }
          },
          "9,0": {
            "size": [
              1,
              1
            ],
            "content": {
              "_type": "Boolean Box",
              "_source0": "network_table:///climber-table/Left at Bottom",
              "_title": "/Left at Bottom",
              "_glyph": 148,
              "_showGlyph": false,
              "Colors/Color when true": "#7CFC00FF",
              "Colors/Color when false": "#8B0000FF"
            }
          },
          "0,1": {
            "size": [
              1,
              1
            ],
            "content": {
              "_type": "Boolean Box",
              "_source0": "network_table:///climber-table/Right at Bottom",
              "_title": "/Right at Bottom",
              "_glyph": 148,
              "_showGlyph": false,
              "Colors/Color when true": "#7CFC00FF",
              "Colors/Color when false": "#8B0000FF"
            }
          }
        }
      }
    },
    {
      "title": "Drive Train",
      "autoPopulate": true,
      "autoPopulatePrefix": "drive-train",
      "widgetPane": {
        "gridSize": 128.0,
        "showGrid": true,
        "hgap": 16.0,
        "vgap": 16.0,
        "titleType": 0,
        "tiles": {
          "0,0": {
            "size": [
              1,
              1
            ],
            "content": {
              "_type": "Text View",
              "_source0": "network_table:///drive-train/Robot x",
              "_title": "/Robot x",
              "_glyph": 148,
              "_showGlyph": false
            }
          },
          "1,0": {
            "size": [
              1,
              1
            ],
            "content": {
              "_type": "Text View",
              "_source0": "network_table:///drive-train/Robot y",
              "_title": "/Robot y",
              "_glyph": 148,
              "_showGlyph": false
            }
          },
          "2,0": {
            "size": [
              1,
              1
            ],
            "content": {
              "_type": "Text View",
              "_source0": "network_table:///drive-train/Robot theta",
              "_title": "/Robot theta",
              "_glyph": 148,
              "_showGlyph": false
            }
          },
          "3,0": {
            "size": [
              1,
              1
            ],
            "content": {
              "_type": "Text View",
              "_source0": "network_table:///drive-train/Pigeon Pitch",
              "_title": "/Pigeon Pitch",
              "_glyph": 148,
              "_showGlyph": false
            }
          },
          "4,0": {
            "size": [
              1,
              1
            ],
            "content": {
              "_type": "Text View",
              "_source0": "network_table:///drive-train/Pigeon Yaw",
              "_title": "/Pigeon Yaw",
              "_glyph": 148,
              "_showGlyph": false
            }
          },
          "5,0": {
            "size": [
              1,
              1
            ],
            "content": {
              "_type": "Text View",
              "_source0": "network_table:///drive-train/Pigeon Roll",
              "_title": "/Pigeon Roll",
              "_glyph": 148,
              "_showGlyph": false
            }
          },
          "6,0": {
            "size": [
              1,
              1
            ],
            "content": {
              "_type": "Text View",
              "_source0": "network_table:///drive-train/FLturningOffset",
              "_title": "/FLturningOffset",
              "_glyph": 148,
              "_showGlyph": false
            }
          },
          "7,0": {
            "size": [
              1,
              1
            ],
            "content": {
              "_type": "Text View",
              "_source0": "network_table:///drive-train/FLturningSetpoint",
              "_title": "/FLturningSetpoint",
              "_glyph": 148,
              "_showGlyph": false
            }
          },
          "8,0": {
            "size": [
              1,
              1
            ],
            "content": {
              "_type": "Text View",
              "_source0": "network_table:///drive-train/FLdriveSetpoint",
              "_title": "/FLdriveSetpoint",
              "_glyph": 148,
              "_showGlyph": false
            }
          },
          "9,0": {
            "size": [
              1,
              1
            ],
            "content": {
              "_type": "Text View",
              "_source0": "network_table:///drive-train/FRturningOffset",
              "_title": "/FRturningOffset",
              "_glyph": 148,
              "_showGlyph": false
            }
          },
          "10,0": {
            "size": [
              1,
              1
            ],
            "content": {
              "_type": "Text View",
              "_source0": "network_table:///drive-train/FRturningSetpoint",
              "_title": "/FRturningSetpoint",
              "_glyph": 148,
              "_showGlyph": false
            }
          },
          "11,0": {
            "size": [
              1,
              1
            ],
            "content": {
              "_type": "Text View",
              "_source0": "network_table:///drive-train/FRdriveSetpoint",
              "_title": "/FRdriveSetpoint",
              "_glyph": 148,
              "_showGlyph": false
            }
          },
          "12,0": {
            "size": [
              1,
              1
            ],
            "content": {
              "_type": "Text View",
              "_source0": "network_table:///drive-train/BRturningOffset",
              "_title": "/BRturningOffset",
              "_glyph": 148,
              "_showGlyph": false
            }
          },
          "0,1": {
            "size": [
              1,
              1
            ],
            "content": {
              "_type": "Text View",
              "_source0": "network_table:///drive-train/BRturningSetpoint",
              "_title": "/BRturningSetpoint",
              "_glyph": 148,
              "_showGlyph": false
            }
          },
          "1,1": {
            "size": [
              1,
              1
            ],
            "content": {
              "_type": "Text View",
              "_source0": "network_table:///drive-train/BRdriveSetpoint",
              "_title": "/BRdriveSetpoint",
              "_glyph": 148,
              "_showGlyph": false
            }
          },
          "2,1": {
            "size": [
              1,
              1
            ],
            "content": {
              "_type": "Text View",
              "_source0": "network_table:///drive-train/BLturningOffset",
              "_title": "/BLturningOffset",
              "_glyph": 148,
              "_showGlyph": false
            }
          },
          "3,1": {
            "size": [
              1,
              1
            ],
            "content": {
              "_type": "Text View",
              "_source0": "network_table:///drive-train/BLturningSetpoint",
              "_title": "/BLturningSetpoint",
              "_glyph": 148,
              "_showGlyph": false
            }
          },
          "4,1": {
            "size": [
              1,
              1
            ],
            "content": {
              "_type": "Text View",
              "_source0": "network_table:///drive-train/BLdriveSetpoint",
              "_title": "/BLdriveSetpoint",
              "_glyph": 148,
              "_showGlyph": false
            }
          },
          "5,1": {
            "size": [
              1,
              1
            ],
            "content": {
              "_type": "Text View",
              "_source0": "network_table:///drive-train/FL Abs Encoder",
              "_title": "/FL Abs Encoder",
              "_glyph": 148,
              "_showGlyph": false
            }
          },
          "6,1": {
            "size": [
              1,
              1
            ],
            "content": {
              "_type": "Text View",
              "_source0": "network_table:///drive-train/FR Abs Encoder",
              "_title": "/FR Abs Encoder",
              "_glyph": 148,
              "_showGlyph": false
            }
          },
          "7,1": {
            "size": [
              1,
              1
            ],
            "content": {
              "_type": "Text View",
              "_source0": "network_table:///drive-train/BR Abs Encoder",
              "_title": "/BR Abs Encoder",
              "_glyph": 148,
              "_showGlyph": false
            }
          },
          "8,1": {
            "size": [
              1,
              1
            ],
            "content": {
              "_type": "Text View",
              "_source0": "network_table:///drive-train/BL Abs Encoder",
              "_title": "/BL Abs Encoder",
              "_glyph": 148,
              "_showGlyph": false
            }
          },
          "9,1": {
            "size": [
              1,
              1
            ],
            "content": {
              "_type": "Text View",
              "_source0": "network_table:///drive-train/Rotation Current Angle",
              "_title": "/Rotation Current Angle",
              "_glyph": 148,
              "_showGlyph": false
            }
          },
          "10,1": {
            "size": [
              1,
              1
            ],
            "content": {
              "_type": "Text View",
              "_source0": "network_table:///drive-train/Rotation Target Angle",
              "_title": "/Rotation Target Angle",
              "_glyph": 148,
              "_showGlyph": false
            }
          },
          "11,1": {
            "size": [
              1,
              1
            ],
            "content": {
              "_type": "Text View",
              "_source0": "network_table:///drive-train/Rotation Power Input",
              "_title": "/Rotation Power Input",
              "_glyph": 148,
              "_showGlyph": false
            }
          },
          "0,2": {
            "size": [
              1,
              1
            ],
            "content": {
              "_type": "Text View",
              "_source0": "network_table:///drive-train/Rotation Controller P",
              "_title": "/Rotation Controller P",
              "_glyph": 148,
              "_showGlyph": false
            }
          },
          "1,2": {
            "size": [
              1,
              1
            ],
            "content": {
              "_type": "Text View",
              "_source0": "network_table:///drive-train/Rotation Controller Position Error",
              "_title": "/Rotation Controller Position Error",
              "_glyph": 148,
              "_showGlyph": false
            }
          },
          "2,2": {
            "size": [
              1,
              1
            ],
            "content": {
              "_type": "Text View",
              "_source0": "network_table:///drive-train/Rotation Controller Setpoint",
              "_title": "/Rotation Controller Setpoint",
              "_glyph": 148,
              "_showGlyph": false
            }
          },
          "3,2": {
            "size": [
              1,
              1
            ],
            "content": {
              "_type": "Text View",
              "_source0": "network_table:///drive-train/Rotation Filtered Target Angle",
              "_title": "/Rotation Filtered Target Angle",
              "_glyph": 148,
              "_showGlyph": false
            }
          },
          "4,2": {
            "size": [
              1,
              1
            ],
            "content": {
              "_type": "Boolean Box",
              "_source0": "network_table:///drive-train/is Drive Abs Working",
              "_title": "/is Drive Abs Working",
              "_glyph": 148,
              "_showGlyph": false,
              "Colors/Color when true": "#7CFC00FF",
              "Colors/Color when false": "#8B0000FF"
            }
          }
        }
      }
    },
    {
      "title": "Pose Estimator",
      "autoPopulate": true,
      "autoPopulatePrefix": "pose-estimator-table",
      "widgetPane": {
        "gridSize": 128.0,
        "showGrid": true,
        "hgap": 16.0,
        "vgap": 16.0,
        "titleType": 0,
        "tiles": {}
      }
    },
    {
      "title": "Snuffilator",
      "autoPopulate": true,
      "autoPopulatePrefix": "snuffy-table",
      "widgetPane": {
        "gridSize": 128.0,
        "showGrid": true,
        "hgap": 16.0,
        "vgap": 16.0,
        "titleType": 0,
        "tiles": {}
      }
    }
  ],
  "windowGeometry": {
    "x": 0.800000011920929,
    "y": 0.800000011920929,
    "width": 1534.4000244140625,
    "height": 814.4000244140625
  }
}